te2rules/__init__.py
te2rules/adapter.py
te2rules/explainer.py
te2rules/rule.py
te2rules/tree.py
te2rules-1.0.1.dist-info/LICENSE
te2rules-1.0.1.dist-info/METADATA
te2rules-1.0.1.dist-info/WHEEL
te2rules-1.0.1.dist-info/top_level.txt
te2rules-1.0.1.dist-info/RECORD
