Metadata-Version: 2.1
Name: te2rules
Version: 1.0.1
Summary: Python Library to explain tree ensembles using rules
Home-page: https://github.com/linkedin/TE2Rules
Author: G Roshan Lal
Author-email: groshanlal@gmail.com
License: Creative Commons Attribution-NonCommercial 4.0 International Public License
Project-URL: Bug Tracker, https://github.com/linkedin/TE2Rules/issues
Project-URL: Source Code, https://github.com/linkedin/TE2Rules
Classifier: Programming Language :: Python :: 3
Classifier: License :: OSI Approved :: Common Public License
Classifier: Topic :: Scientific/Engineering :: Artificial Intelligence
Classifier: Topic :: Software Development :: Libraries :: Python Modules
Requires-Python: >=3.6
License-File: LICENSE
Requires-Dist: numpy (>=1.19.1)
Requires-Dist: pandas (>=1.2.4)
Requires-Dist: scikit-learn (>=1.0.1)
Requires-Dist: six (>=1.15.0)
Requires-Dist: tqdm (>=4.43.0)
Requires-Dist: xgboost (>=1.4.2)
